EffectiveGoZhongwenban/README.md
EffectiveGoZhongwenban/__init__.py
EffectiveGoZhongwenban/__main__.py
EffectiveGoZhongwenban/file.epub
EffectiveGoZhongwenban/index.html
EffectiveGoZhongwenban/css/__init__.py
EffectiveGoZhongwenban/css/annotations.css
EffectiveGoZhongwenban/css/main.css
EffectiveGoZhongwenban/css/normalize.css
EffectiveGoZhongwenban/css/popup.css
EffectiveGoZhongwenban/font/__init__.py
EffectiveGoZhongwenban/font/fontello.eot
EffectiveGoZhongwenban/font/fontello.svg
EffectiveGoZhongwenban/font/fontello.ttf
EffectiveGoZhongwenban/font/fontello.woff
EffectiveGoZhongwenban/img/__init__.py
EffectiveGoZhongwenban/img/annotator-glyph-sprite.png
EffectiveGoZhongwenban/img/annotator-icon-sprite.png
EffectiveGoZhongwenban/img/apple-touch-icon.png
EffectiveGoZhongwenban/img/cancelfullscreen.png
EffectiveGoZhongwenban/img/close.png
EffectiveGoZhongwenban/img/fullscreen.png
EffectiveGoZhongwenban/img/loader.gif
EffectiveGoZhongwenban/img/menu-icon.png
EffectiveGoZhongwenban/img/save.png
EffectiveGoZhongwenban/img/saved.png
EffectiveGoZhongwenban/img/settings-s.png
EffectiveGoZhongwenban/img/settings.png
EffectiveGoZhongwenban/img/star.png
EffectiveGoZhongwenban/js/__init__.py
EffectiveGoZhongwenban/js/epub.js
EffectiveGoZhongwenban/js/epub.min.js
EffectiveGoZhongwenban/js/epub.min.map
EffectiveGoZhongwenban/js/hooks.min.js
EffectiveGoZhongwenban/js/hooks.min.map
EffectiveGoZhongwenban/js/reader.js
EffectiveGoZhongwenban/js/reader.js.map
EffectiveGoZhongwenban/js/reader.min.js
EffectiveGoZhongwenban/js/reader.min.map
EffectiveGoZhongwenban/js/hooks/__init__.py
EffectiveGoZhongwenban/js/hooks/extensions/__init__.py
EffectiveGoZhongwenban/js/hooks/extensions/highlight.js
EffectiveGoZhongwenban/js/libs/__init__.py
EffectiveGoZhongwenban/js/libs/jquery.min.js
EffectiveGoZhongwenban/js/libs/localforage.min.js
EffectiveGoZhongwenban/js/libs/screenfull.js
EffectiveGoZhongwenban/js/libs/screenfull.min.js
EffectiveGoZhongwenban/js/libs/zip.min.js
effective_go_zhongwenban-2024.3.1.0.dist-info/METADATA
effective_go_zhongwenban-2024.3.1.0.dist-info/WHEEL
effective_go_zhongwenban-2024.3.1.0.dist-info/entry_points.txt
effective_go_zhongwenban-2024.3.1.0.dist-info/top_level.txt
effective_go_zhongwenban-2024.3.1.0.dist-info/RECORD
